LICENSE
MANIFEST.in
README.md
pyproject.toml
setup.py
bin/cosmosis
bin/cosmosis-campaign
bin/cosmosis-configure
bin/cosmosis-extract
bin/cosmosis-postprocess
bin/cosmosis-sample-fisher
cosmosis/Makefile
cosmosis/__init__.py
cosmosis/campaign.py
cosmosis/configure.py
cosmosis/constants.py
cosmosis/gaussian_likelihood.py
cosmosis/main.py
cosmosis/names.py
cosmosis/postprocess.py
cosmosis/table.py
cosmosis/utils.py
cosmosis/version.py
cosmosis.egg-info/PKG-INFO
cosmosis.egg-info/SOURCES.txt
cosmosis.egg-info/dependency_links.txt
cosmosis.egg-info/requires.txt
cosmosis.egg-info/top_level.txt
cosmosis/config/compilers.mk
cosmosis/config/subdirs.mk
cosmosis/datablock/Makefile
cosmosis/datablock/__init__.py
cosmosis/datablock/c_datablock.cc
cosmosis/datablock/c_datablock.h
cosmosis/datablock/clamp.hh
cosmosis/datablock/cosmosis_constants.fh
cosmosis/datablock/cosmosis_constants.h
cosmosis/datablock/cosmosis_modules.F90
cosmosis/datablock/cosmosis_section_names.F90
cosmosis/datablock/cosmosis_types.F90
cosmosis/datablock/cosmosis_wrappers.F90
cosmosis/datablock/datablock.cc
cosmosis/datablock/datablock.hh
cosmosis/datablock/datablock_logging.cc
cosmosis/datablock/datablock_logging.h
cosmosis/datablock/datablock_status.h
cosmosis/datablock/datablock_types.h
cosmosis/datablock/entry.cc
cosmosis/datablock/entry.hh
cosmosis/datablock/exceptions.hh
cosmosis/datablock/generate_sections.py
cosmosis/datablock/handler.c
cosmosis/datablock/ndarray.hh
cosmosis/datablock/section.cc
cosmosis/datablock/section.hh
cosmosis/datablock/section_names.h
cosmosis/datablock/section_names.txt
cosmosis/datablock/cosmosis_py/__init__.py
cosmosis/datablock/cosmosis_py/block.py
cosmosis/datablock/cosmosis_py/dbt_types.py
cosmosis/datablock/cosmosis_py/errors.py
cosmosis/datablock/cosmosis_py/lib.py
cosmosis/datablock/cosmosis_py/section_names.py
cosmosis/output/__init__.py
cosmosis/output/astropy_output.py
cosmosis/output/cosmomc_output.py
cosmosis/output/fits_output.py
cosmosis/output/in_memory_output.py
cosmosis/output/null_output.py
cosmosis/output/output_base.py
cosmosis/output/text_output.py
cosmosis/output/utils.py
cosmosis/plotting/__init__.py
