Metadata-Version: 2.4
Name: cosmosis
Version: 3.23
Summary: The CosmoSIS parameter estimation library.
Home-page: https://github.com/joezuntz/cosmosis
Author: Joe Zuntz
Author-email: joezuntz@googlemail.com
License-File: LICENSE
Requires-Dist: pyyaml
Requires-Dist: emcee
Requires-Dist: numpy
Requires-Dist: scipy
Requires-Dist: matplotlib
Requires-Dist: pybind11
Requires-Dist: pyyaml
Requires-Dist: scipy
Requires-Dist: threadpoolctl
Requires-Dist: emcee
Requires-Dist: dynesty
Requires-Dist: zeus-mcmc
Requires-Dist: nautilus-sampler>=1.0.1
Requires-Dist: dulwich
Requires-Dist: scikit-learn
Requires-Dist: Py-BOBYQA
Dynamic: author
Dynamic: author-email
Dynamic: home-page
Dynamic: license-file
Dynamic: requires-dist
Dynamic: summary
